setup.cfg
setup.py
src/audio_ui.egg-info/PKG-INFO
src/audio_ui.egg-info/SOURCES.txt
src/audio_ui.egg-info/dependency_links.txt
src/audio_ui.egg-info/requires.txt
src/audio_ui.egg-info/top_level.txt
src/elements/__init__.py
src/elements/button.py
src/elements/checkbox.py
src/elements/element.py
src/elements/menu.py
src/elements/menu_bar.py
src/elements/text_box.py
src/elements/text_label.py
src/elements/toggle_button.py
src/screens/__init__.py
src/screens/container_screen.py
src/screens/dialog.py
src/screens/screen.py
src/utils/__init__.py
src/utils/key_handler.py
src/utils/speech_manager.py
test/test_state_machine.py
test/test_window.py